[
{
  "model": "member.authuser",
  "pk": 2,
  "fields": {
    "password": "pbkdf2_sha256$260000$B4izrSL5cMDhpz76Ml8oAd$y+vALyJB3hKoOGYietAefzmZQMA0TSPrbGq4WLI7yvs=",
    "last_login": "2021-05-31T13:34:39.971Z",
    "is_superuser": false,
    "person": 3,
    "email": "pick@leader.com",
    "date_joined": "2021-05-26T21:26:41.699Z",
    "is_active": true,
    "is_staff": true,
    "groups": [],
    "user_permissions": []
  }
},
{
  "model": "member.authuser",
  "pk": 3,
  "fields": {
    "password": "",
    "last_login": null,
    "is_superuser": false,
    "person": 4,
    "email": "volunteer@picker.com",
    "date_joined": "2021-05-31T13:38:14.213Z",
    "is_active": true,
    "is_staff": false,
    "groups": [],
    "user_permissions": []
  }
},
{
  "model": "member.authuser",
  "pk": 4,
  "fields": {
    "password": "pbkdf2_sha256$260000$XSSo62sasEikkh7QT6pmhP$0euWqhRjDM+odkonz31c62r3ozp5Nm2tB6UyB20d7PA=",
    "last_login": null,
    "is_superuser": false,
    "person": 5,
    "email": "core@member.com",
    "date_joined": "2021-06-14T18:16:06.369Z",
    "is_active": true,
    "is_staff": true,
    "groups": [
      1
    ],
    "user_permissions": []
  }
}
]
